duel/__init__.py
duel/expr.py
duel/help.md
duel/help.py
duel/parser.py
pretty_printer/__init__.py
gdb_tools-1.5.dist-info/LICENSE
gdb_tools-1.5.dist-info/METADATA
gdb_tools-1.5.dist-info/WHEEL
gdb_tools-1.5.dist-info/top_level.txt
gdb_tools-1.5.dist-info/RECORD
