Metadata-Version: 2.1
Name: gdb-tools
Version: 1.5
Summary: Various tools to improve the gdb experience
Home-page: https://github.com/vuvova/gdb-tools
Author: Sergei Golubchik
Author-email: vuvova@gmail.com
Classifier: Development Status :: 5 - Production/Stable
Classifier: Environment :: Plugins
Classifier: Intended Audience :: Developers
Classifier: License :: OSI Approved :: BSD License
Classifier: Programming Language :: Python
Classifier: Programming Language :: Python :: 2
Classifier: Programming Language :: Python :: 3
Classifier: Topic :: Software Development :: Debuggers
License-File: LICENSE
Requires-Dist: arpeggio
